LICENSE
README.md
setup.py
CuttApi/Cuttshort.py
CuttApi/__init__.py
CuttApi.egg-info/PKG-INFO
CuttApi.egg-info/SOURCES.txt
CuttApi.egg-info/dependency_links.txt
CuttApi.egg-info/requires.txt
CuttApi.egg-info/top_level.txt