Metadata-Version: 2.1
Name: CuttApi
Version: 1.0
Summary: One of the best ways of shortening URLs using Cuttly URL shortener just by entering your API key and seeing the rest that is done automatically by the Module
Home-page: https://github.com/devrajdevs/CuttApi
Download-URL: https://github.com/devrajdevs/CuttApi/archive/refs/tags/v1.0.tar.gz
Author: Devraj Therani
Author-email: ttctlc96e@mozmail.com
License: MIT
Keywords: API,SIMPLE,URL,SHORTENER
Classifier: Development Status :: 5 - Production/Stable
Classifier: Intended Audience :: Developers
Classifier: Topic :: Software Development :: Build Tools
Classifier: License :: OSI Approved :: MIT License
Classifier: Programming Language :: Python :: 3
Classifier: Programming Language :: Python :: 3.6
Classifier: Programming Language :: Python :: 3.7
Classifier: Programming Language :: Python :: 3.8
Classifier: Programming Language :: Python :: 3.9
Classifier: Programming Language :: Python :: 3.10
License-File: LICENSE
Requires-Dist: requests
Requires-Dist: urllib3
Requires-Dist: pyperclip
